<?xml version="1.0" encoding="UTF-8" standalone="yes"?><node artifactManager="be.nabu.eai.module.web.component.WebComponentManager" created="2020-05-18T11:23:10.259+02:00" lastModified="2020-05-18T11:26:08.647+02:00" leaf="true" version="4"><environmentId>apollo</environmentId><hidden>false</hidden><properties/><references>nabu.misc.auditing.manage.rest.listAllServices</references><references>nabu.misc.auditing.manage.rest.listAuditServices</references><references>nabu.misc.auditing.manage.rest.listAuditedServices</references><references>nabu.misc.auditing.manage.rest.startAudit</references><references>nabu.misc.auditing.manage.rest.stopAudit</references></node>